Metadata-Version: 2.1
Name: prajwal-lib
Version: 0.2
Summary: lib to cheat in ml exam
Home-page: UNKNOWN
Author-email: prajsa99@gmail.com
License: UNKNOWN
Platform: UNKNOWN
